fri/__init__.py
fri/compute.py
fri/main.py
fri/model/__init__.py
fri/model/base_cvxproblem.py
fri/model/base_initmodel.py
fri/model/base_lupi.py
fri/model/base_type.py
fri/model/classification.py
fri/model/lupi_classification.py
fri/model/lupi_ordinal_regression.py
fri/model/lupi_regression.py
fri/model/ordinal_regression.py
fri/model/regression.py
fri/parameter_searcher.py
fri/plot.py
fri/tests/test_FRI.py
fri/tests/test_feature_selection.py
fri/tests/test_grouping.py
fri/tests/test_lupi.py
fri/tests/test_parameter_searcher.py
fri/tests/test_preset.py
fri/tests/test_score.py
fri/utils.py
fri-9.0.0.dist-info/LICENSE
fri-9.0.0.dist-info/METADATA
fri-9.0.0.dist-info/WHEEL
fri-9.0.0.dist-info/RECORD
