Metadata-Version: 2.3
Name: fri
Version: 9.0.0
Summary: Implementation of Feature Relevance Bounds method to perform Feature Selection and further analysis.
License: MIT
Keywords: feature selection,linear models,machine learning
Author: Lukas Pfannschmidt
Author-email: lukas@lpfann.me
Requires-Python: >=3.9,<4.0
Classifier: Development Status :: 4 - Beta
Classifier: Intended Audience :: Developers
Classifier: Intended Audience :: Science/Research
Classifier: License :: OSI Approved :: MIT License
Classifier: Programming Language :: Python :: 3
Classifier: Programming Language :: Python :: 3.9
Classifier: Programming Language :: Python :: 3.10
Classifier: Programming Language :: Python :: 3.11
Classifier: Programming Language :: Python :: 3.12
Classifier: Programming Language :: Python :: 3.13
Classifier: Topic :: Scientific/Engineering :: Bio-Informatics
Classifier: Topic :: Scientific/Engineering :: Information Analysis
Classifier: Topic :: Scientific/Engineering :: Medical Science Apps.
Requires-Dist: arfs-gen (>=1.2,<2.0)
Requires-Dist: cvxpy (>=1.5,<2.0)
Requires-Dist: ecos (>=2.0.7,<3.0.0)
Requires-Dist: joblib (>=1,<2)
Requires-Dist: matplotlib (>=3.1,<4.0)
Requires-Dist: numpy (>=1.21,<1.27)
Requires-Dist: scikit-learn (>=1.0,<2.0)
Requires-Dist: scipy (>=1.0,<2.0)
Project-URL: Homepage, https://fri.lpfann.me
Project-URL: Repository, https://github.com/lpfann/fri
